iv2/__init__.py
iv2/model.py
iv2/schemas.py
iv2-0.0.1.dist-info/METADATA
iv2-0.0.1.dist-info/WHEEL
iv2-0.0.1.dist-info/top_level.txt
iv2-0.0.1.dist-info/RECORD
